{
	"name": "raw_unimed_core",
	"properties": {
		"activities": [
			{
				"name": "CargaVenta1",
				"type": "Copy",
				"dependsOn": [],
				"policy": {
					"timeout": "0.12:00:00",
					"retry": 0,
					"retryIntervalInSeconds": 30,
					"secureOutput": false,
					"secureInput": false
				},
				"userProperties": [],
				"typeProperties": {
					"source": {
						"type": "ExcelSource",
						"storeSettings": {
							"type": "AzureBlobFSReadSettings",
							"recursive": true,
							"enablePartitionDiscovery": false
						}
					},
					"sink": {
						"type": "ParquetSink",
						"storeSettings": {
							"type": "AzureBlobFSWriteSettings",
							"maxConcurrentConnections": 2,
							"copyBehavior": "FlattenHierarchy"
						},
						"formatSettings": {
							"type": "ParquetWriteSettings"
						}
					},
					"enableStaging": false,
					"translator": {
						"type": "TabularTranslator",
						"mappings": [
							{
								"source": {
									"name": "FECHA",
									"type": "String",
									"physicalType": "String"
								},
								"sink": {
									"name": "FECHA",
									"type": "String",
									"physicalType": "UTF8"
								}
							},
							{
								"source": {
									"name": "DISTRIBUIDOR",
									"type": "String",
									"physicalType": "String"
								},
								"sink": {
									"name": "DISTRIBUIDOR",
									"type": "String",
									"physicalType": "UTF8"
								}
							},
							{
								"source": {
									"name": "GP",
									"type": "String",
									"physicalType": "String"
								},
								"sink": {
									"name": "GP",
									"type": "String",
									"physicalType": "UTF8"
								}
							},
							{
								"source": {
									"name": "ST",
									"type": "String",
									"physicalType": "String"
								},
								"sink": {
									"name": "ST",
									"type": "String",
									"physicalType": "UTF8"
								}
							},
							{
								"source": {
									"name": "FAMILIA",
									"type": "String",
									"physicalType": "String"
								},
								"sink": {
									"name": "FAMILIA",
									"type": "String",
									"physicalType": "UTF8"
								}
							},
							{
								"source": {
									"name": "COD_SAP",
									"type": "String",
									"physicalType": "String"
								},
								"sink": {
									"name": "COD_SAP",
									"type": "String",
									"physicalType": "UTF8"
								}
							},
							{
								"source": {
									"name": "DESC_SAP",
									"type": "String",
									"physicalType": "String"
								},
								"sink": {
									"name": "DESC_SAP",
									"type": "String",
									"physicalType": "UTF8"
								}
							},
							{
								"source": {
									"name": "RUC",
									"type": "String",
									"physicalType": "String"
								},
								"sink": {
									"name": "RUC",
									"type": "String",
									"physicalType": "UTF8"
								}
							},
							{
								"source": {
									"name": "CLIENTE",
									"type": "String",
									"physicalType": "String"
								},
								"sink": {
									"name": "CLIENTE",
									"type": "String",
									"physicalType": "UTF8"
								}
							},
							{
								"source": {
									"name": "ZONA",
									"type": "String",
									"physicalType": "String"
								},
								"sink": {
									"name": "ZONA",
									"type": "String",
									"physicalType": "UTF8"
								}
							},
							{
								"source": {
									"name": "TIPO VTA",
									"type": "String",
									"physicalType": "String"
								},
								"sink": {
									"name": "TIPO VTA",
									"type": "String",
									"physicalType": "UTF8"
								}
							},
							{
								"source": {
									"name": "TIPO DATO",
									"type": "String",
									"physicalType": "String"
								},
								"sink": {
									"name": "TIPO DATO",
									"type": "String",
									"physicalType": "UTF8"
								}
							},
							{
								"source": {
									"name": "VALOR",
									"type": "String",
									"physicalType": "String"
								},
								"sink": {
									"name": "VALOR",
									"type": "String",
									"physicalType": "UTF8"
								}
							},
							{
								"source": {
									"name": "FECREGISTRO",
									"type": "String"
								},
								"sink": {
									"name": "FECREGISTRO",
									"type": "String",
									"physicalType": "UTF8"
								}
							},
							{
								"source": {
									"name": "OWNER",
									"type": "String"
								},
								"sink": {
									"name": "OWNER",
									"type": "String",
									"physicalType": "UTF8"
								}
							}
						],
						"typeConversion": true,
						"typeConversionSettings": {
							"allowDataTruncation": true,
							"treatBooleanAsNumber": false
						}
					}
				},
				"inputs": [
					{
						"referenceName": "DS_VENTA1_XLS",
						"type": "DatasetReference",
						"parameters": {
							"zona": "raw",
							"directorio": "unimed/venta",
							"archivo": "ALFARO_2021.xlsx"
						}
					}
				],
				"outputs": [
					{
						"referenceName": "DS_VENTA1_PARQUET",
						"type": "DatasetReference",
						"parameters": {
							"zona": "master",
							"directorio": "unimed",
							"archivo": "venta.parquet"
						}
					}
				]
			}
		],
		"folder": {
			"name": "01_raw_source"
		},
		"annotations": []
	}
}